{
  "generated_at": "2026-05-14T07:15:00.000Z",
  "date": "14/05/2026",
  "scan_summary": {
    "competitors_scanned": 43,
    "changes_detected": 15,
    "high_impact": 2,
    "medium_impact": 13,
    "low_impact": 0
  },
  "monitoring_areas": [
    { "slug": "product_features", "label": "Product Features", "count": 1 },
    { "slug": "pricing_models", "label": "Pricing Models", "count": 0 },
    { "slug": "seo_content", "label": "SEO & Content", "count": 0 },
    { "slug": "ux_conversion", "label": "UX & Conversion", "count": 14 },
    { "slug": "market_launches", "label": "Market Launches", "count": 0 }
  ],
  "segments": [
    { "slug": "sports_betting", "label": "Sports Betting", "flag": "🇺🇸" },
    { "slug": "casino", "label": "Casino", "flag": "🇺🇸" },
    { "slug": "state_affiliate", "label": "State Affiliate", "flag": "🇺🇸" },
    { "slug": "sports_data_fantasy", "label": "Sports Data/Fantasy", "flag": "🇺🇸" },
    { "slug": "odds_comparison", "label": "Odds Comparison", "flag": "🇬🇧" },
    { "slug": "news_hybrid", "label": "News/Hybrid", "flag": "🇬🇧" }
  ],
  "competitors": [
    {
      "id": "thelines",
      "name": "The Lines",
      "domain": "thelines.com",
      "url": "https://www.thelines.com/",
      "segment": "sports_betting",
      "segment_label": "Sports Betting",
      "flag": "🇺🇸",
      "color": "#E74C3C",
      "initials": "TL",
      "last_scanned": "2026-05-12T07:05:56.000Z",
      "changes": [
        {
          "title": "New footer links added",
          "description": "New links: Best NBA Player Props Today: Wendell Carter Tops Card, Best NHL Prop Bets & Anytime Goal Scorer Picks Today, 04/19, Magic Shock Pistons in Game 1 to Shift East Playoff Series, Orlando Magic vs. Detroit Pistons Odds, Picks & Predictions",
          "area": "seo_content",
          "area_label": "SEO & Content",
          "impact": "low",
          "detected_at": "2026-04-20T07:05:40.000Z",
          "url": "https://www.thelines.com/"
        },
        {
          "title": "Feature/tool presence changed",
          "description": "Free-to-play element disappeared",
          "area": "product_features",
          "area_label": "Product Features",
          "impact": "high",
          "detected_at": "2026-04-21T07:06:09.000Z",
          "url": "https://www.thelines.com/"
        },
        {
          "title": "New footer links added",
          "description": "New links: Best NBA Player Props Today: James Harden Shines Again, Colorado Looks to Restrict Sports Betting Ads, Is SpinQuest Giveaway Worth the Hype?`We Gave it a Try, Victor Wembanyama Avoids Suspension Ahead of Game 5",
          "area": "seo_content",
          "area_label": "SEO & Content",
          "impact": "low",
          "detected_at": "2026-05-12T07:05:56.000Z",
          "url": "https://www.thelines.com/"
        }
      ]
    },
    {
      "id": "covers",
      "name": "Covers",
      "domain": "covers.com",
      "url": "https://www.covers.com/",
      "segment": "sports_betting",
      "segment_label": "Sports Betting",
      "flag": "🇺🇸",
      "color": "#C0392B",
      "initials": "CO",
      "last_scanned": "2026-05-14T07:05:06.000Z",
      "changes": [
        {
          "title": "CTA/button text changed",
          "description": "New CTAs: NBA Betting Forum, NCAAB Betting Forum | Removed: No Code Needed, View Matchup",
          "area": "ux_conversion",
          "area_label": "UX & Conversion",
          "impact": "medium",
          "detected_at": "2026-04-23T07:04:54.000Z",
          "url": "https://www.covers.com/"
        },
        {
          "title": "Navigation structure changed",
          "description": "Top-level items: 8 → 9",
          "area": "ux_conversion",
          "area_label": "UX & Conversion",
          "impact": "high",
          "detected_at": "2026-05-12T07:05:56.000Z",
          "url": "https://www.covers.com/"
        },
        {
          "title": "CTA/button text changed",
          "description": "New CTAs: Find my match, Join the conversation, NBA Betting Forum, NCAAB Betting Forum, NFL Betting Forum | Removed: Claim $10, Claim $100, Claim $20, Claim $50, Continue with Google",
          "area": "ux_conversion",
          "area_label": "UX & Conversion",
          "impact": "medium",
          "detected_at": "2026-05-14T07:05:06.000Z",
          "url": "https://www.covers.com/"
        }
      ]
    },
    {
      "id": "vegasinsider",
      "name": "Vegas Insider",
      "domain": "vegasinsider.com",
      "url": "https://www.vegasinsider.com/",
      "segment": "sports_betting",
      "segment_label": "Sports Betting",
      "flag": "🇺🇸",
      "color": "#3498DB",
      "initials": "VI",
      "last_scanned": "2026-05-14T07:05:06.000Z",
      "changes": [
        {
          "title": "Feature/tool presence changed",
          "description": "Search bar disappeared",
          "area": "product_features",
          "area_label": "Product Features",
          "impact": "high",
          "detected_at": "2026-04-20T07:05:40.000Z",
          "url": "https://www.vegasinsider.com/"
        },
        {
          "title": "Page layout restructured",
          "description": "sections: 6 → 2",
          "area": "ux_conversion",
          "area_label": "UX & Conversion",
          "impact": "medium",
          "detected_at": "2026-04-20T07:05:40.000Z",
          "url": "https://www.vegasinsider.com/"
        },
        {
          "title": "CTA/button text changed",
          "description": "Removed: View Full Analysis",
          "area": "ux_conversion",
          "area_label": "UX & Conversion",
          "impact": "medium",
          "detected_at": "2026-04-21T07:06:09.000Z",
          "url": "https://www.vegasinsider.com/"
        },
        {
          "title": "Feature/tool presence changed",
          "description": "Search bar appeared",
          "area": "product_features",
          "area_label": "Product Features",
          "impact": "high",
          "detected_at": "2026-04-21T07:06:09.000Z",
          "url": "https://www.vegasinsider.com/"
        },
        {
          "title": "Page layout restructured",
          "description": "sections: 2 → 6",
          "area": "ux_conversion",
          "area_label": "UX & Conversion",
          "impact": "medium",
          "detected_at": "2026-04-21T07:06:09.000Z",
          "url": "https://www.vegasinsider.com/"
        },
        {
          "title": "CTA/button text changed",
          "description": "New CTAs: View Full Analysis",
          "area": "ux_conversion",
          "area_label": "UX & Conversion",
          "impact": "medium",
          "detected_at": "2026-04-23T07:04:54.000Z",
          "url": "https://www.vegasinsider.com/"
        },
        {
          "title": "Feature/tool presence changed",
          "description": "Search bar appeared",
          "area": "product_features",
          "area_label": "Product Features",
          "impact": "high",
          "detected_at": "2026-05-12T07:05:56.000Z",
          "url": "https://www.vegasinsider.com/"
        },
        {
          "title": "Page layout restructured",
          "description": "sections: 2 → 6",
          "area": "ux_conversion",
          "area_label": "UX & Conversion",
          "impact": "medium",
          "detected_at": "2026-05-12T07:05:56.000Z",
          "url": "https://www.vegasinsider.com/"
        },
        {
          "title": "CTA/button text changed",
          "description": "New CTAs: View Full Analysis",
          "area": "ux_conversion",
          "area_label": "UX & Conversion",
          "impact": "medium",
          "detected_at": "2026-05-14T07:05:06.000Z",
          "url": "https://www.vegasinsider.com/"
        }
      ]
    },
    {
      "id": "pickswise",
      "name": "Pickswise",
      "domain": "pickswise.com",
      "url": "https://www.pickswise.com/",
      "segment": "sports_betting",
      "segment_label": "Sports Betting",
      "flag": "🇺🇸",
      "color": "#2ECC71",
      "initials": "PW",
      "last_scanned": "2026-05-12T07:05:56.000Z",
      "changes": [
        {
          "title": "Page layout restructured",
          "description": "sections: 5 → 8",
          "area": "ux_conversion",
          "area_label": "UX & Conversion",
          "impact": "medium",
          "detected_at": "2026-04-20T07:05:40.000Z",
          "url": "https://www.pickswise.com/"
        },
        {
          "title": "Structured data types changed",
          "description": "New: SportsEvent",
          "area": "seo_content",
          "area_label": "SEO & Content",
          "impact": "low",
          "detected_at": "2026-04-20T07:05:40.000Z",
          "url": "https://www.pickswise.com/"
        },
        {
          "title": "Feature/tool presence changed",
          "description": "Ratings/scores appeared",
          "area": "product_features",
          "area_label": "Product Features",
          "impact": "high",
          "detected_at": "2026-04-21T07:06:09.000Z",
          "url": "https://www.pickswise.com/"
        },
        {
          "title": "Page layout restructured",
          "description": "sections: 8 → 12, main_divs: 4 → 8",
          "area": "ux_conversion",
          "area_label": "UX & Conversion",
          "impact": "medium",
          "detected_at": "2026-04-21T07:06:09.000Z",
          "url": "https://www.pickswise.com/"
        },
        {
          "title": "Page layout restructured",
          "description": "sections: 9 → 12, main_divs: 4 → 7",
          "area": "ux_conversion",
          "area_label": "UX & Conversion",
          "impact": "medium",
          "detected_at": "2026-05-12T07:05:56.000Z",
          "url": "https://www.pickswise.com/"
        }
      ]
    },
    {
      "id": "gamingtoday",
      "name": "Gaming Today",
      "domain": "gamingtoday.com",
      "url": "https://www.gamingtoday.com/",
      "segment": "sports_betting",
      "segment_label": "Sports Betting",
      "flag": "🇺🇸",
      "color": "#F1C40F",
      "initials": "GT",
      "last_scanned": "2026-05-14T07:05:06.000Z",
      "changes": [
        {
          "title": "Homepage headline (H1) changed",
          "description": "Was: \"Gaming Today – America's Home for Gambling News & Reviews\" → Now: \"Gaming Today - America's Home for Gambling News & Reviews\"",
          "area": "ux_conversion",
          "area_label": "UX & Conversion",
          "impact": "medium",
          "detected_at": "2026-05-12T07:05:56.000Z",
          "url": "https://www.gamingtoday.com/"
        },
        {
          "title": "Navigation menu changed",
          "description": "Added: Bally Bet, Best Online Sports Betting Sites, Best Sportsbook Promos, BetMGM, BetRivers, Caesars | Removed: Bet365 Sportsbook Review, BetMGM Sportsbook Review, BetRivers Sportsbook Review, Caesars Sportsbook Review, College Basketball Betting Apps, College Football Betting Apps",
          "area": "ux_conversion",
          "area_label": "UX & Conversion",
          "impact": "high",
          "detected_at": "2026-05-12T07:05:56.000Z",
          "url": "https://www.gamingtoday.com/"
        },
        {
          "title": "Navigation structure changed",
          "description": "Top-level items: 7 → 6",
          "area": "ux_conversion",
          "area_label": "UX & Conversion",
          "impact": "high",
          "detected_at": "2026-05-12T07:05:56.000Z",
          "url": "https://www.gamingtoday.com/"
        },
        {
          "title": "CTA/button text changed",
          "description": "New CTAs: Best Sports Betting Apps, Top Sports Betting Bonuses | Removed: Read More News »",
          "area": "ux_conversion",
          "area_label": "UX & Conversion",
          "impact": "medium",
          "detected_at": "2026-05-12T07:05:56.000Z",
          "url": "https://www.gamingtoday.com/"
        },
        {
          "title": "Page layout restructured",
          "description": "articles: 3 → 0",
          "area": "ux_conversion",
          "area_label": "UX & Conversion",
          "impact": "medium",
          "detected_at": "2026-05-12T07:05:56.000Z",
          "url": "https://www.gamingtoday.com/"
        },
        {
          "title": "Footer navigation changed",
          "description": "Link count: 18 → 10",
          "area": "seo_content",
          "area_label": "SEO & Content",
          "impact": "low",
          "detected_at": "2026-05-12T07:05:56.000Z",
          "url": "https://www.gamingtoday.com/"
        },
        {
          "title": "Navigation menu changed",
          "description": "Added: MLB Betting Apps | Removed: Sports Betting",
          "area": "ux_conversion",
          "area_label": "UX & Conversion",
          "impact": "high",
          "detected_at": "2026-05-14T07:05:06.000Z",
          "url": "https://www.gamingtoday.com/"
        }
      ]
    },
    {
      "id": "bettingpros",
      "name": "Betting Pros",
      "domain": "bettingpros.com",
      "url": "https://www.bettingpros.com/",
      "segment": "sports_betting",
      "segment_label": "Sports Betting",
      "flag": "🇺🇸",
      "color": "#16A085",
      "initials": "BP",
      "last_scanned": "2026-05-14T07:05:06.000Z",
      "changes": [
        {
          "title": "CTA/button text changed",
          "description": "Removed: View Tool ›",
          "area": "ux_conversion",
          "area_label": "UX & Conversion",
          "impact": "medium",
          "detected_at": "2026-05-14T07:05:06.000Z",
          "url": "https://www.bettingpros.com/"
        },
        {
          "title": "Feature/tool presence changed",
          "description": "Search bar disappeared",
          "area": "product_features",
          "area_label": "Product Features",
          "impact": "high",
          "detected_at": "2026-05-14T07:05:06.000Z",
          "url": "https://www.bettingpros.com/"
        },
        {
          "title": "Page layout restructured",
          "description": "sections: 28 → 24",
          "area": "ux_conversion",
          "area_label": "UX & Conversion",
          "impact": "medium",
          "detected_at": "2026-05-14T07:05:06.000Z",
          "url": "https://www.bettingpros.com/"
        }
      ]
    },
    {
      "id": "casino_org",
      "name": "Casino.org",
      "domain": "casino.org",
      "url": "https://www.casino.org/",
      "segment": "casino",
      "segment_label": "Casino",
      "flag": "🇺🇸",
      "color": "#EC407A",
      "initials": "CA",
      "last_scanned": "2026-05-14T07:05:06.000Z",
      "changes": [
        {
          "title": "CTA/button text changed",
          "description": "New CTAs: See all casinos to avoid | Removed: All Casino Game ShowsCS",
          "area": "ux_conversion",
          "area_label": "UX & Conversion",
          "impact": "medium",
          "detected_at": "2026-05-12T07:05:56.000Z",
          "url": "https://www.casino.org/"
        },
        {
          "title": "Page layout restructured",
          "description": "articles: 3 → 0",
          "area": "ux_conversion",
          "area_label": "UX & Conversion",
          "impact": "medium",
          "detected_at": "2026-05-12T07:05:56.000Z",
          "url": "https://www.casino.org/"
        },
        {
          "title": "CTA/button text changed",
          "description": "New CTAs: See all casinos to avoid | Removed: All Casino Game ShowsCS",
          "area": "ux_conversion",
          "area_label": "UX & Conversion",
          "impact": "medium",
          "detected_at": "2026-05-14T07:05:06.000Z",
          "url": "https://www.casino.org/"
        },
        {
          "title": "Page layout restructured",
          "description": "articles: 3 → 0",
          "area": "ux_conversion",
          "area_label": "UX & Conversion",
          "impact": "medium",
          "detected_at": "2026-05-14T07:05:06.000Z",
          "url": "https://www.casino.org/"
        }
      ]
    },
    {
      "id": "onlinegambling",
      "name": "Online Gambling",
      "domain": "onlinegambling.com",
      "url": "https://www.onlinegambling.com/",
      "segment": "casino",
      "segment_label": "Casino",
      "flag": "🇺🇸",
      "color": "#9B59B6",
      "initials": "OG",
      "last_scanned": "2026-05-12T07:05:56.000Z",
      "changes": [
        {
          "title": "CTA/button text changed",
          "description": "New CTAs: 150% Boost: 250,000 GC + 25 SC + Elixir & Claw Credits | Removed: 150% extra gold",
          "area": "ux_conversion",
          "area_label": "UX & Conversion",
          "impact": "medium",
          "detected_at": "2026-04-20T07:05:40.000Z",
          "url": "https://www.onlinegambling.com/"
        },
        {
          "title": "CTA/button text changed",
          "description": "New CTAs: Claim now | Removed: Play for real",
          "area": "ux_conversion",
          "area_label": "UX & Conversion",
          "impact": "medium",
          "detected_at": "2026-04-23T07:04:54.000Z",
          "url": "https://www.onlinegambling.com/"
        },
        {
          "title": "Navigation menu changed",
          "description": "Added: Big Pirate | Removed: SweepNext",
          "area": "ux_conversion",
          "area_label": "UX & Conversion",
          "impact": "high",
          "detected_at": "2026-05-12T07:05:56.000Z",
          "url": "https://www.onlinegambling.com/"
        }
      ]
    },
    {
      "id": "usgamblingsites",
      "name": "US Gambling Sites",
      "domain": "usgamblingsites.com",
      "url": "https://www.usgamblingsites.com/",
      "segment": "casino",
      "segment_label": "Casino",
      "flag": "🇺🇸",
      "color": "#00ACC1",
      "initials": "UG",
      "last_scanned": "2026-05-12T07:05:56.000Z",
      "changes": [
        {
          "title": "Feature/tool presence changed",
          "description": "Ratings/scores appeared",
          "area": "product_features",
          "area_label": "Product Features",
          "impact": "high",
          "detected_at": "2026-05-12T07:05:56.000Z",
          "url": "https://www.usgamblingsites.com/"
        },
        {
          "title": "Page layout restructured",
          "description": "sections: 16 → 28, articles: 0 → 6",
          "area": "ux_conversion",
          "area_label": "UX & Conversion",
          "impact": "medium",
          "detected_at": "2026-05-12T07:05:56.000Z",
          "url": "https://www.usgamblingsites.com/"
        }
      ]
    },
    {
      "id": "playusa",
      "name": "Play USA",
      "domain": "playusa.com",
      "url": "https://www.playusa.com/",
      "segment": "casino",
      "segment_label": "Casino",
      "flag": "🇺🇸",
      "color": "#8E44AD",
      "initials": "PU",
      "last_scanned": "2026-05-14T07:05:06.000Z",
      "changes": [
        {
          "title": "Page layout restructured",
          "description": "sidebar added",
          "area": "ux_conversion",
          "area_label": "UX & Conversion",
          "impact": "medium",
          "detected_at": "2026-04-21T07:06:09.000Z",
          "url": "https://www.playusa.com/"
        },
        {
          "title": "CTA/button text changed",
          "description": "New CTAs: BetMGM Casino, BetRivers Casino, Caesars Online Casino, Crown Coins Casino, DraftKings Casino | Removed: $1 Deposit Casinos, Free craps online, Free spins bonuses, Guide to Online Slots, How to play the Powerball online",
          "area": "ux_conversion",
          "area_label": "UX & Conversion",
          "impact": "medium",
          "detected_at": "2026-05-14T07:05:06.000Z",
          "url": "https://www.playusa.com/"
        },
        {
          "title": "Page layout restructured",
          "description": "accordion added",
          "area": "ux_conversion",
          "area_label": "UX & Conversion",
          "impact": "medium",
          "detected_at": "2026-05-14T07:05:06.000Z",
          "url": "https://www.playusa.com/"
        }
      ]
    },
    {
      "id": "playillinois",
      "name": "Play Illinois",
      "domain": "playillinois.com",
      "url": "https://www.playillinois.com/",
      "segment": "state_affiliate",
      "segment_label": "State Affiliate",
      "flag": "🇺🇸",
      "color": "#F39C12",
      "initials": "PI",
      "last_scanned": "2026-04-21T07:06:09.000Z",
      "changes": [
        {
          "title": "CTA/button text changed",
          "description": "New CTAs: Bet $5 Get $250, Bet $5 Get $250 If Your Bet Wins, BetMGM Sportsbook Review | Removed: Caesars Sportsbook Review, Double Your Winnings, On Your Next 10 Wagers",
          "area": "ux_conversion",
          "area_label": "UX & Conversion",
          "impact": "medium",
          "detected_at": "2026-04-20T07:05:40.000Z",
          "url": "https://www.playillinois.com/"
        },
        {
          "title": "CTA/button text changed",
          "description": "New CTAs: Caesars Sportsbook Review, Double Your Winnings, On Your Next 10 Wagers | Removed: Bet $5 Get $250, Bet $5 Get $250 If Your Bet Wins, BetMGM Sportsbook Review",
          "area": "ux_conversion",
          "area_label": "UX & Conversion",
          "impact": "medium",
          "detected_at": "2026-04-21T07:06:09.000Z",
          "url": "https://www.playillinois.com/"
        }
      ]
    },
    {
      "id": "playohio",
      "name": "Play Ohio",
      "domain": "playohio.com",
      "url": "https://www.playohio.com/",
      "segment": "state_affiliate",
      "segment_label": "State Affiliate",
      "flag": "🇺🇸",
      "color": "#D35400",
      "initials": "PO",
      "last_scanned": "2026-05-14T07:05:06.000Z",
      "changes": [
        {
          "title": "Page layout restructured",
          "description": "sidebar added",
          "area": "ux_conversion",
          "area_label": "UX & Conversion",
          "impact": "medium",
          "detected_at": "2026-04-21T07:06:09.000Z",
          "url": "https://www.playohio.com/"
        },
        {
          "title": "CTA/button text changed",
          "description": "New CTAs: Filter By Sweepstakes CasinosSportsbooks | Removed: Filter BySweepstakes CasinosSportsbooks",
          "area": "ux_conversion",
          "area_label": "UX & Conversion",
          "impact": "medium",
          "detected_at": "2026-05-14T07:05:06.000Z",
          "url": "https://www.playohio.com/"
        }
      ]
    },
    {
      "id": "playindiana",
      "name": "Play Indiana",
      "domain": "playindiana.com",
      "url": "https://www.playindiana.com/",
      "segment": "state_affiliate",
      "segment_label": "State Affiliate",
      "flag": "🇺🇸",
      "color": "#FF7043",
      "initials": "PN",
      "last_scanned": "2026-05-14T07:05:06.000Z",
      "changes": [
        {
          "title": "CTA/button text changed",
          "description": "New CTAs: 250,000 Gold Coins, 250,000 Gold Coins PLUS 25 Stake Cash | Removed: 30 FREE SC, With 1,500,000 GC Purchase for $9.99",
          "area": "ux_conversion",
          "area_label": "UX & Conversion",
          "impact": "medium",
          "detected_at": "2026-05-12T07:05:56.000Z",
          "url": "https://www.playindiana.com/"
        },
        {
          "title": "CTA/button text changed",
          "description": "New CTAs: Get 1.5M GC + 30 Free SC, On First $9.99 Purchase | Removed: 250,000 Gold Coins, 250,000 Gold Coins PLUS 25 Stake Cash",
          "area": "ux_conversion",
          "area_label": "UX & Conversion",
          "impact": "medium",
          "detected_at": "2026-05-14T07:05:06.000Z",
          "url": "https://www.playindiana.com/"
        }
      ]
    },
    {
      "id": "rotogrinders",
      "name": "Roto Grinders",
      "domain": "rotogrinders.com",
      "url": "https://rotogrinders.com/",
      "segment": "sports_data_fantasy",
      "segment_label": "Sports Data/Fantasy",
      "flag": "🇺🇸",
      "color": "#1ABC9C",
      "initials": "RG",
      "last_scanned": "2026-05-14T07:05:06.000Z",
      "changes": [
        {
          "title": "CTA/button text changed",
          "description": "New CTAs: Coming Friday, Coming Thursday, Coming Tuesday, Coming Wednesday | Removed: To Be Announced",
          "area": "ux_conversion",
          "area_label": "UX & Conversion",
          "impact": "medium",
          "detected_at": "2026-04-20T07:05:40.000Z",
          "url": "https://rotogrinders.com/"
        },
        {
          "title": "CTA/button text changed",
          "description": "Removed: Coming Tuesday",
          "area": "ux_conversion",
          "area_label": "UX & Conversion",
          "impact": "medium",
          "detected_at": "2026-04-21T07:06:09.000Z",
          "url": "https://rotogrinders.com/"
        },
        {
          "title": "CTA/button text changed",
          "description": "New CTAs: Buy Now, GET THE PICKS | Removed: Coming Thursday",
          "area": "ux_conversion",
          "area_label": "UX & Conversion",
          "impact": "medium",
          "detected_at": "2026-04-23T07:04:54.000Z",
          "url": "https://rotogrinders.com/"
        },
        {
          "title": "CTA/button text changed",
          "description": "Removed: Coming Tuesday",
          "area": "ux_conversion",
          "area_label": "UX & Conversion",
          "impact": "medium",
          "detected_at": "2026-05-12T07:05:56.000Z",
          "url": "https://rotogrinders.com/"
        },
        {
          "title": "CTA/button text changed",
          "description": "Removed: Coming Thursday",
          "area": "ux_conversion",
          "area_label": "UX & Conversion",
          "impact": "medium",
          "detected_at": "2026-05-14T07:05:06.000Z",
          "url": "https://rotogrinders.com/"
        }
      ]
    },
    {
      "id": "fantasypros",
      "name": "Fantasy Pros",
      "domain": "fantasypros.com",
      "url": "https://www.fantasypros.com/",
      "segment": "sports_data_fantasy",
      "segment_label": "Sports Data/Fantasy",
      "flag": "🇺🇸",
      "color": "#E67E22",
      "initials": "FP",
      "last_scanned": "2026-05-14T07:05:06.000Z",
      "changes": [
        {
          "title": "Homepage headline (H1) changed",
          "description": "Was: \"Dream NFL Draft Landing Spots\" → Now: \"Erickson's NFL Mock Draft\"",
          "area": "ux_conversion",
          "area_label": "UX & Conversion",
          "impact": "medium",
          "detected_at": "2026-04-20T07:05:40.000Z",
          "url": "https://www.fantasypros.com/"
        },
        {
          "title": "Homepage headline (H1) changed",
          "description": "Was: \"Erickson's NFL Mock Draft\" → Now: \"DBro's Top 100 Dynasty Rookie Rankings\"",
          "area": "ux_conversion",
          "area_label": "UX & Conversion",
          "impact": "medium",
          "detected_at": "2026-04-21T07:06:09.000Z",
          "url": "https://www.fantasypros.com/"
        },
        {
          "title": "Feature/tool presence changed",
          "description": "Video embed appeared",
          "area": "product_features",
          "area_label": "Product Features",
          "impact": "high",
          "detected_at": "2026-04-21T07:06:09.000Z",
          "url": "https://www.fantasypros.com/"
        },
        {
          "title": "Homepage headline (H1) changed",
          "description": "Was: \"DBro's Top 100 Dynasty Rookie Rankings\" → Now: \"50 Stats to Know: 2026 NFL Draft Class\"",
          "area": "ux_conversion",
          "area_label": "UX & Conversion",
          "impact": "medium",
          "detected_at": "2026-04-23T07:04:54.000Z",
          "url": "https://www.fantasypros.com/"
        },
        {
          "title": "Feature/tool presence changed",
          "description": "Video embed disappeared",
          "area": "product_features",
          "area_label": "Product Features",
          "impact": "high",
          "detected_at": "2026-04-23T07:04:54.000Z",
          "url": "https://www.fantasypros.com/"
        },
        {
          "title": "Homepage headline (H1) changed",
          "description": "Was: \"Early Rookie Predictions\" → Now: \"DBro's Dynasty Rookie Draft Primers\"",
          "area": "ux_conversion",
          "area_label": "UX & Conversion",
          "impact": "medium",
          "detected_at": "2026-05-12T07:05:56.000Z",
          "url": "https://www.fantasypros.com/"
        },
        {
          "title": "Homepage headline (H1) changed",
          "description": "Was: \"DBro's Dynasty Rookie Draft Primers\" → Now: \"Dynasty Players to Buy & Sell\"",
          "area": "ux_conversion",
          "area_label": "UX & Conversion",
          "impact": "medium",
          "detected_at": "2026-05-14T07:05:06.000Z",
          "url": "https://www.fantasypros.com/"
        }
      ]
    },
    {
      "id": "freebets",
      "name": "Free Bets",
      "domain": "freebets.com",
      "url": "https://www.freebets.com/",
      "segment": "odds_comparison",
      "segment_label": "Odds Comparison",
      "flag": "🇬🇧",
      "color": "#34495E",
      "initials": "FB",
      "last_scanned": "2026-05-14T07:05:06.000Z",
      "changes": [
        {
          "title": "CTA/button text changed",
          "description": "New CTAs: Join Now | Removed: ZSKAON",
          "area": "ux_conversion",
          "area_label": "UX & Conversion",
          "impact": "medium",
          "detected_at": "2026-04-20T07:05:40.000Z",
          "url": "https://www.freebets.com/"
        },
        {
          "title": "CTA/button text changed",
          "description": "New CTAs: YSKAST | Removed: Join Now",
          "area": "ux_conversion",
          "area_label": "UX & Conversion",
          "impact": "medium",
          "detected_at": "2026-04-23T07:04:54.000Z",
          "url": "https://www.freebets.com/"
        },
        {
          "title": "CTA/button text changed",
          "description": "New CTAs: Show 48 results, World Cup Betting Offers | Removed: Show 47 results, World Cup 2026 Hub",
          "area": "ux_conversion",
          "area_label": "UX & Conversion",
          "impact": "medium",
          "detected_at": "2026-05-12T07:05:56.000Z",
          "url": "https://www.freebets.com/"
        },
        {
          "title": "CTA/button text changed",
          "description": "New CTAs: YSKAST | Removed: Join Now",
          "area": "ux_conversion",
          "area_label": "UX & Conversion",
          "impact": "medium",
          "detected_at": "2026-05-14T07:05:06.000Z",
          "url": "https://www.freebets.com/"
        }
      ]
    },
    {
      "id": "igamingbusiness",
      "name": "iGaming Business",
      "domain": "igamingbusiness.com",
      "url": "https://igamingbusiness.com/",
      "segment": "news_hybrid",
      "segment_label": "News/Hybrid",
      "flag": "🇬🇧",
      "color": "#27AE60",
      "initials": "IB",
      "last_scanned": "2026-04-23T07:04:54.000Z",
      "changes": [
        {
          "title": "New footer links added",
          "description": "New links: Analysis, Are virtual games the new heart of the lobby?, H2GC: Prediction markets – Overhyped and underperforming?",
          "area": "seo_content",
          "area_label": "SEO & Content",
          "impact": "low",
          "detected_at": "2026-04-23T07:04:54.000Z",
          "url": "https://igamingbusiness.com/"
        }
      ]
    }
  ],
  "recent_changes": [
    {
      "competitor_name": "Covers",
      "competitor_initials": "CO",
      "competitor_color": "#C0392B",
      "title": "CTA/button text changed",
      "description": "New CTAs: Find my match, Join the conversation, NBA Betting Forum, NCAAB Betting Forum, NFL Betting Forum | Removed: Claim $10, Claim $100, Claim $20, Claim $50, Continue with Google",
      "area": "ux_conversion",
      "area_label": "UX & Conversion",
      "impact": "medium",
      "detected_at": "2026-05-14T07:05:06.000Z",
      "url": "https://www.covers.com/"
    },
    {
      "competitor_name": "Vegas Insider",
      "competitor_initials": "VI",
      "competitor_color": "#3498DB",
      "title": "CTA/button text changed",
      "description": "New CTAs: View Full Analysis",
      "area": "ux_conversion",
      "area_label": "UX & Conversion",
      "impact": "medium",
      "detected_at": "2026-05-14T07:05:06.000Z",
      "url": "https://www.vegasinsider.com/"
    },
    {
      "competitor_name": "Gaming Today",
      "competitor_initials": "GT",
      "competitor_color": "#F1C40F",
      "title": "Navigation menu changed",
      "description": "Added: MLB Betting Apps | Removed: Sports Betting",
      "area": "ux_conversion",
      "area_label": "UX & Conversion",
      "impact": "high",
      "detected_at": "2026-05-14T07:05:06.000Z",
      "url": "https://www.gamingtoday.com/"
    },
    {
      "competitor_name": "Betting Pros",
      "competitor_initials": "BP",
      "competitor_color": "#16A085",
      "title": "CTA/button text changed",
      "description": "Removed: View Tool ›",
      "area": "ux_conversion",
      "area_label": "UX & Conversion",
      "impact": "medium",
      "detected_at": "2026-05-14T07:05:06.000Z",
      "url": "https://www.bettingpros.com/"
    },
    {
      "competitor_name": "Betting Pros",
      "competitor_initials": "BP",
      "competitor_color": "#16A085",
      "title": "Feature/tool presence changed",
      "description": "Search bar disappeared",
      "area": "product_features",
      "area_label": "Product Features",
      "impact": "high",
      "detected_at": "2026-05-14T07:05:06.000Z",
      "url": "https://www.bettingpros.com/"
    },
    {
      "competitor_name": "Betting Pros",
      "competitor_initials": "BP",
      "competitor_color": "#16A085",
      "title": "Page layout restructured",
      "description": "sections: 28 → 24",
      "area": "ux_conversion",
      "area_label": "UX & Conversion",
      "impact": "medium",
      "detected_at": "2026-05-14T07:05:06.000Z",
      "url": "https://www.bettingpros.com/"
    },
    {
      "competitor_name": "Casino.org",
      "competitor_initials": "CA",
      "competitor_color": "#EC407A",
      "title": "CTA/button text changed",
      "description": "New CTAs: See all casinos to avoid | Removed: All Casino Game ShowsCS",
      "area": "ux_conversion",
      "area_label": "UX & Conversion",
      "impact": "medium",
      "detected_at": "2026-05-14T07:05:06.000Z",
      "url": "https://www.casino.org/"
    },
    {
      "competitor_name": "Casino.org",
      "competitor_initials": "CA",
      "competitor_color": "#EC407A",
      "title": "Page layout restructured",
      "description": "articles: 3 → 0",
      "area": "ux_conversion",
      "area_label": "UX & Conversion",
      "impact": "medium",
      "detected_at": "2026-05-14T07:05:06.000Z",
      "url": "https://www.casino.org/"
    },
    {
      "competitor_name": "Play USA",
      "competitor_initials": "PU",
      "competitor_color": "#8E44AD",
      "title": "CTA/button text changed",
      "description": "New CTAs: BetMGM Casino, BetRivers Casino, Caesars Online Casino, Crown Coins Casino, DraftKings Casino | Removed: $1 Deposit Casinos, Free craps online, Free spins bonuses, Guide to Online Slots, How to play the Powerball online",
      "area": "ux_conversion",
      "area_label": "UX & Conversion",
      "impact": "medium",
      "detected_at": "2026-05-14T07:05:06.000Z",
      "url": "https://www.playusa.com/"
    },
    {
      "competitor_name": "Play USA",
      "competitor_initials": "PU",
      "competitor_color": "#8E44AD",
      "title": "Page layout restructured",
      "description": "accordion added",
      "area": "ux_conversion",
      "area_label": "UX & Conversion",
      "impact": "medium",
      "detected_at": "2026-05-14T07:05:06.000Z",
      "url": "https://www.playusa.com/"
    },
    {
      "competitor_name": "Play Indiana",
      "competitor_initials": "PN",
      "competitor_color": "#FF7043",
      "title": "CTA/button text changed",
      "description": "New CTAs: Get 1.5M GC + 30 Free SC, On First $9.99 Purchase | Removed: 250,000 Gold Coins, 250,000 Gold Coins PLUS 25 Stake Cash",
      "area": "ux_conversion",
      "area_label": "UX & Conversion",
      "impact": "medium",
      "detected_at": "2026-05-14T07:05:06.000Z",
      "url": "https://www.playindiana.com/"
    },
    {
      "competitor_name": "Play Ohio",
      "competitor_initials": "PO",
      "competitor_color": "#D35400",
      "title": "CTA/button text changed",
      "description": "New CTAs: Filter By Sweepstakes CasinosSportsbooks | Removed: Filter BySweepstakes CasinosSportsbooks",
      "area": "ux_conversion",
      "area_label": "UX & Conversion",
      "impact": "medium",
      "detected_at": "2026-05-14T07:05:06.000Z",
      "url": "https://www.playohio.com/"
    },
    {
      "competitor_name": "Roto Grinders",
      "competitor_initials": "RG",
      "competitor_color": "#1ABC9C",
      "title": "CTA/button text changed",
      "description": "Removed: Coming Thursday",
      "area": "ux_conversion",
      "area_label": "UX & Conversion",
      "impact": "medium",
      "detected_at": "2026-05-14T07:05:06.000Z",
      "url": "https://rotogrinders.com/"
    },
    {
      "competitor_name": "Fantasy Pros",
      "competitor_initials": "FP",
      "competitor_color": "#E67E22",
      "title": "Homepage headline (H1) changed",
      "description": "Was: \"DBro's Dynasty Rookie Draft Primers\" → Now: \"Dynasty Players to Buy & Sell\"",
      "area": "ux_conversion",
      "area_label": "UX & Conversion",
      "impact": "medium",
      "detected_at": "2026-05-14T07:05:06.000Z",
      "url": "https://www.fantasypros.com/"
    },
    {
      "competitor_name": "Free Bets",
      "competitor_initials": "FB",
      "competitor_color": "#34495E",
      "title": "CTA/button text changed",
      "description": "New CTAs: YSKAST | Removed: Join Now",
      "area": "ux_conversion",
      "area_label": "UX & Conversion",
      "impact": "medium",
      "detected_at": "2026-05-14T07:05:06.000Z",
      "url": "https://www.freebets.com/"
    }
  ]
}
